cfclient/__init__.py
cfclient/gui.py
cfclient/headless.py
cfclient/version.py
cfclient/configs/config.json
cfclient/configs/input/Generic_OS_X.json
cfclient/configs/input/Joystick.json
cfclient/configs/input/PS3_Mode_1.json
cfclient/configs/input/PS3_Mode_2.json
cfclient/configs/input/PS3_Mode_3.json
cfclient/configs/input/PS4_Mode_1.json
cfclient/configs/input/PS4_Mode_2.json
cfclient/configs/input/PS4_shoulder_btns_yaw.json
cfclient/configs/input/xbox360_mode1.json
cfclient/configs/log/stabilizer.json
cfclient/configs/log/PID_tuning/Attitude.json
cfclient/configs/log/PID_tuning/Attitude_rate.json
cfclient/configs/log/PID_tuning/Position.json
cfclient/configs/log/PID_tuning/Velocity.json
cfclient/configs/log/PID_tuning_components/Pitch.json
cfclient/configs/log/PID_tuning_components/Pitch_rate.json
cfclient/configs/log/PID_tuning_components/Position_x.json
cfclient/configs/log/PID_tuning_components/Position_y.json
cfclient/configs/log/PID_tuning_components/Position_z.json
cfclient/configs/log/PID_tuning_components/Roll.json
cfclient/configs/log/PID_tuning_components/Roll_rate.json
cfclient/configs/log/PID_tuning_components/Velocity_x.json
cfclient/configs/log/PID_tuning_components/Velocity_y.json
cfclient/configs/log/PID_tuning_components/Velocity_z.json
cfclient/configs/log/PID_tuning_components/Yaw.json
cfclient/configs/log/PID_tuning_components/Yaw_rate.json
cfclient/resources/log_param_doc.json
cfclient/resources/map.html
cfclient/resources/map.js
cfclient/ui/__init__.py
cfclient/ui/connectivity_manager.py
cfclient/ui/main.py
cfclient/ui/main.ui
cfclient/ui/pluginhelper.py
cfclient/ui/pose_logger.py
cfclient/ui/tab_toolbox.py
cfclient/ui/dialogs/__init__.py
cfclient/ui/dialogs/about.py
cfclient/ui/dialogs/about.ui
cfclient/ui/dialogs/anchor_position_dialog.py
cfclient/ui/dialogs/anchor_position_dialog.ui
cfclient/ui/dialogs/basestation_mode_dialog.py
cfclient/ui/dialogs/basestation_mode_dialog.ui
cfclient/ui/dialogs/bootloader.py
cfclient-2025.9.dist-info/licenses/LICENSE.txt
cfclient-2025.9.dist-info/METADATA
cfclient-2025.9.dist-info/WHEEL
cfclient-2025.9.dist-info/entry_points.txt
cfclient-2025.9.dist-info/top_level.txt
cfclient-2025.9.dist-info/RECORD
